openhab/Actions.py
openhab/Addons.py
openhab/Audio.py
openhab/Auth.py
openhab/ChannelTypes.py
openhab/Client.py
openhab/ConfigDescriptions.py
openhab/Discovery.py
openhab/Events.py
openhab/Iconsets.py
openhab/Inbox.py
openhab/Items.py
openhab/Links.py
openhab/Logging.py
openhab/ModuleTypes.py
openhab/Persistence.py
openhab/ProfileTypes.py
openhab/Rules.py
openhab/Services.py
openhab/Sitemaps.py
openhab/Systeminfo.py
openhab/Tags.py
openhab/Templates.py
openhab/ThingTypes.py
openhab/Things.py
openhab/Transformations.py
openhab/UI.py
openhab/UUID.py
openhab/Voice.py
openhab/__init__.py
openhab/tests/Actions.py
openhab/tests/Addons.py
openhab/tests/Audio.py
openhab/tests/Auth.py
openhab/tests/ChannelEvents.py
openhab/tests/ChannelTypes.py
openhab/tests/ConfigDescriptions.py
openhab/tests/Discovery.py
openhab/tests/Events.py
openhab/tests/Iconsets.py
openhab/tests/Inbox.py
openhab/tests/InboxEvents.py
openhab/tests/ItemEvents.py
openhab/tests/Items.py
openhab/tests/LinkEvents.py
openhab/tests/Links.py
openhab/tests/Logging.py
openhab/tests/ModuleTypes.py
openhab/tests/Persistence.py
openhab/tests/ProfileTypes.py
openhab/tests/Rules.py
openhab/tests/Services.py
openhab/tests/Sitemaps.py
openhab/tests/Systeminfo.py
openhab/tests/Tags.py
openhab/tests/Templates.py
openhab/tests/ThingEvents.py
openhab/tests/ThingTypes.py
openhab/tests/Things.py
openhab/tests/Transformations.py
openhab/tests/UI.py
openhab/tests/UUID.py
openhab/tests/Voice.py
openhab/tests/__init__.py
tests/Actions.py
tests/Addons.py
tests/Audio.py
tests/Auth.py
tests/ChannelEvents.py
tests/ChannelTypes.py
tests/ConfigDescriptions.py
tests/Discovery.py
tests/Events.py
tests/Iconsets.py
tests/Inbox.py
tests/InboxEvents.py
tests/ItemEvents.py
tests/Items.py
tests/LinkEvents.py
tests/Links.py
tests/Logging.py
tests/ModuleTypes.py
tests/Persistence.py
tests/ProfileTypes.py
tests/Rules.py
tests/Services.py
tests/Sitemaps.py
tests/Systeminfo.py
tests/Tags.py
tests/Templates.py
tests/ThingEvents.py
python_openhab_rest_client-0.2.4.dist-info/LICENSE
python_openhab_rest_client-0.2.4.dist-info/METADATA
python_openhab_rest_client-0.2.4.dist-info/WHEEL
python_openhab_rest_client-0.2.4.dist-info/top_level.txt
python_openhab_rest_client-0.2.4.dist-info/RECORD
