Metadata-Version: 2.1
Name: python-openhab-rest-client
Version: 0.2.4
Summary: A Python client for the openHAB REST API. This library enables easy interaction with the openHAB REST API to control smart home devices, retrieve status information, and process events.
Home-page: https://github.com/Michdo93/python-openhab-rest-client
Author: Michael Christian Dörflinger
Author-email: michaeldoerflinger93@gmail.com
Classifier: Programming Language :: Python :: 3
Classifier: License :: OSI Approved :: MIT License
Classifier: Operating System :: OS Independent
Requires-Python: >=3.6
License-File: LICENSE
Requires-Dist: requests
